aiobrute/__init__.py
aiobrute/__main__.py
aiobrute/actions.py
aiobrute/configs.py
aiobrute/parser.py
aiobrute/utils.py
aiobrute/worker.py
aiobrute/workers/__init__.py
aiobrute/workers/ftp.py
aiobrute/workers/http.py
aiobrute/workers/mysql.py
aiobrute/workers/ssh.py
resources/__init__.py
resources/templates/wp-xmlrpc.jinja2
resources/wordlists/adobe.txt
resources/wordlists/hotmail.txt
resources/wordlists/mostused.txt
resources/wordlists/myspace.txt
resources/wordlists/rockyou.txt
aiobrute-0.1.0.dist-info/LICENSE.txt
aiobrute-0.1.0.dist-info/METADATA
aiobrute-0.1.0.dist-info/WHEEL
aiobrute-0.1.0.dist-info/entry_points.txt
aiobrute-0.1.0.dist-info/top_level.txt
aiobrute-0.1.0.dist-info/RECORD
