Metadata-Version: 2.1
Name: aiobrute
Version: 0.1.0
Summary: A tool for asynchronously testing password login on several protocols
Home-page: https://github.com/jylanglois/aiobrute
Author: Jean-Yann Barsalou-Langlois
Author-email: jeanyann.langlois@gmail.com
License: GNU GPLv3
Project-URL: Bug Tracker, https://github.com/jylanglois/aiobrute/issues
Keywords: infosec,pentesting,security
Platform: UNKNOWN
Classifier: Framework :: AsyncIO
Classifier: Development Status :: 3 - Alpha
Classifier: Programming Language :: Python :: 3
Classifier: Programming Language :: Python :: 3 :: Only
Classifier: Programming Language :: Python :: 3.7
Classifier: Programming Language :: Python :: 3.8
Classifier: Programming Language :: Python :: 3.9
Classifier: Programming Language :: Python :: 3.10
Classifier: License :: OSI Approved :: GNU General Public License v2 (GPLv2)
Classifier: Operating System :: OS Independent
Requires-Python: >=3.7
License-File: LICENSE.txt
Requires-Dist: aiohttp (>=3.7.4)
Requires-Dist: aioftp (>=0.20.1)
Requires-Dist: alive-progress (>=2.0.0)
Requires-Dist: asyncssh (>=2.8.1)
Requires-Dist: beautifulsoup4 (>=4.10.0)
Requires-Dist: Jinja2 (>=3.0.3)
Requires-Dist: schema (>=0.7.5)
Requires-Dist: validators (>=0.18.2)
Requires-Dist: requests (>=2.27.1)
Requires-Dist: aiomysql (>=0.0.22)
Requires-Dist: prettytable (>=3.2.0)
